.gitignore
README.md
requirements.txt
setup.py
wawa_logger/__init__.py
wawa_logger.egg-info/PKG-INFO
wawa_logger.egg-info/SOURCES.txt
wawa_logger.egg-info/dependency_links.txt
wawa_logger.egg-info/top_level.txt
wawa_logger/__pycache__/__init__.cpython-36.pyc