Metadata-Version: 1.0
Name: wawa-logger
Version: 1.7
Summary: internal application
Home-page: UNKNOWN
Author: Nathan Getty
Author-email: gettynathanj@gmail.com
License: UNKNOWN
Platform: UNKNOWN
